encyclopedia/__init__.py
encyclopedia/arboretum.py
encyclopedia/dictionary.py
encyclopedia/eav.py
encyclopedia/forest.py
encyclopedia/kmlfolder.py
encyclopedia/kmlopedia.py
encyclopedia/record.py
encyclopedia/relate.py
encyclopedia/templates.py
encyclopedia/xmlopedia.py
encyclopedia-0.44.dist-info/LICENSE.txt
encyclopedia-0.44.dist-info/METADATA
encyclopedia-0.44.dist-info/WHEEL
encyclopedia-0.44.dist-info/top_level.txt
encyclopedia-0.44.dist-info/RECORD
