Metadata-Version: 2.1
Name: encyclopedia
Version: 0.44
Summary: An Encyclopedia is an abstract container providing relational (and non-relational) data operations using dictionary notation
Home-page: https://github.com/scott-howard-james/encyclopedia
Author: Scott Howard James
Keywords: container functional composition relation
Classifier: Development Status :: 3 - Alpha
Classifier: Intended Audience :: Developers
Classifier: Topic :: Software Development
Classifier: License :: OSI Approved :: Apache Software License
Classifier: Programming Language :: Python :: 3.5
Classifier: Programming Language :: Python :: 3.6
Classifier: Programming Language :: Python :: 3.7
Classifier: Programming Language :: Python :: 3.8
Classifier: Programming Language :: Python :: 3.9
Classifier: Programming Language :: Python :: 3.10
Requires-Python: >=3.5
License-File: LICENSE.txt
Requires-Dist: nits
